[
  {
    "path": "posts/welcome/",
    "title": "Welcome to Criando blog com o pacote Distill",
    "description": "Welcome to our new blog, Criando blog com o pacote Distill. We hope you enjoy \nreading what we have to say!",
    "author": [
      {
        "name": "Nora Jones",
        "url": "https://example.com/norajones"
      }
    ],
    "date": "2021-02-21",
    "categories": [],
    "contents": "\r\n\r\n\r\n\r\n",
    "preview": {},
    "last_modified": "2021-02-21T18:12:12-03:00",
    "input_file": {}
  }
]
